jxdb
