Metadata-Version: 2.1
Name: jxdb
Version: 0.1.1
Summary: Secured Python Json Database
Home-page: https://github.com/ent1tydev/jxdb
Author: xinyc
Author-email: csecinside@proton.me
License: OpenSociety License
Platform: UNKNOWN
Classifier: License :: OSI Approved
Classifier: Programming Language :: Python :: 3
Classifier: Programming Language :: Python :: 3.7
Classifier: Programming Language :: Python :: 3.8
Classifier: Programming Language :: Python :: 3.9
License-File: LICENSE
